setup.cfg
setup.py
StathamQuotes/__init__.py
StathamQuotes/main.py
StathamQuotes.egg-info/PKG-INFO
StathamQuotes.egg-info/SOURCES.txt
StathamQuotes.egg-info/dependency_links.txt
StathamQuotes.egg-info/top_level.txt