Metadata-Version: 2.1
Name: StathamQuotes
Version: 0.0.3
Summary: A useful module
Author: gbu1at
Author-email: bulatchess@mail.ru
